{
    "name":"菲律宾马尼拉",
    "symbol":"PSI_UI",
    "continent":"亚洲",
    "total":32,
    "data":[
        {
            "date":"1989-12-29",
            "open":"1300.07",
            "close":"1110.64",
            "rate":"-14.57%"
        },
        {
            "date":"1990-12-28",
            "open":"1120.76",
            "close":"653.11",
            "rate":"-41.73%"
        },
        {
            "date":"1991-12-27",
            "open":"630.62",
            "close":"1154.26",
            "rate":"83.04%"
        },
        {
            "date":"1992-12-30",
            "open":"1177.10",
            "close":"1256.22",
            "rate":"6.72%"
        },
        {
            "date":"1993-12-29",
            "open":"1282.97",
            "close":"3241.86",
            "rate":"152.68%"
        },
        {
            "date":"1994-12-29",
            "open":"3317.00",
            "close":"2785.81",
            "rate":"-16.01%"
        },
        {
            "date":"1995-12-29",
            "open":"2787.97",
            "close":"2594.18",
            "rate":"-6.95%"
        },
        {
            "date":"1996-12-27",
            "open":"2585.38",
            "close":"3170.56",
            "rate":"22.63%"
        },
        {
            "date":"1997-12-29",
            "open":"3158.75",
            "close":"1869.23",
            "rate":"-40.82%"
        },
        {
            "date":"1998-12-29",
            "open":"1866.16",
            "close":"1968.78",
            "rate":"5.5%"
        },
        {
            "date":"1999-12-29",
            "open":"1969.32",
            "close":"2142.97",
            "rate":"8.82%"
        },
        {
            "date":"2000-12-29",
            "open":"2143.67",
            "close":"1494.50",
            "rate":"-30.28%"
        },
        {
            "date":"2001-12-28",
            "open":"1488.02",
            "close":"1168.08",
            "rate":"-21.5%"
        },
        {
            "date":"2002-12-27",
            "open":"1167.30",
            "close":"1018.41",
            "rate":"-12.76%"
        },
        {
            "date":"2003-12-30",
            "open":"1018.58",
            "close":"1442.37",
            "rate":"41.61%"
        },
        {
            "date":"2004-12-29",
            "open":"1457.06",
            "close":"1822.83",
            "rate":"25.1%"
        },
        {
            "date":"2005-12-29",
            "open":"1822.95",
            "close":"2096.04",
            "rate":"14.98%"
        },
        {
            "date":"2006-12-29",
            "open":"2096.04",
            "close":"2982.54",
            "rate":"42.29%"
        },
        {
            "date":"2007-12-28",
            "open":"2983.77",
            "close":"3621.60",
            "rate":"21.38%"
        },
        {
            "date":"2008-12-24",
            "open":"3625.59",
            "close":"1872.85",
            "rate":"-48.34%"
        },
        {
            "date":"2009-12-29",
            "open":"1925.75",
            "close":"3052.68",
            "rate":"58.52%"
        },
        {
            "date":"2010-12-30",
            "open":"3051.30",
            "close":"4201.14",
            "rate":"37.68%"
        },
        {
            "date":"2011-12-29",
            "open":"4206.01",
            "close":"4371.96",
            "rate":"3.95%"
        },
        {
            "date":"2012-12-28",
            "open":"4371.96",
            "close":"5812.73",
            "rate":"32.95%"
        },
        {
            "date":"2013-12-27",
            "open":"5810.47",
            "close":"5900.74",
            "rate":"1.55%"
        },
        {
            "date":"2014-12-29",
            "open":"5923.72",
            "close":"7243.33",
            "rate":"22.28%"
        },
        {
            "date":"2015-12-29",
            "open":"7282.94",
            "close":"6917.77",
            "rate":"-5.01%"
        },
        {
            "date":"2016-12-29",
            "open":"6954.27",
            "close":"6849.96",
            "rate":"-1.5%"
        },
        {
            "date":"2017-12-29",
            "open":"6834.20",
            "close":"8558.42",
            "rate":"25.23%"
        },
        {
            "date":"2018-12-28",
            "open":"8592.18",
            "close":"7466.02",
            "rate":"-13.11%"
        },
        {
            "date":"2019-12-27",
            "open":"7496.57",
            "close":"7815.26",
            "rate":"4.25%"
        },
        {
            "date":"2020-03-13",
            "open":"7721.26",
            "close":"5793.94",
            "rate":"-24.96%"
        }
    ]
}